pyunixlzw/__init__.py
pyunixlzw/__main__.py
pyunixlzw/compress.py
pyunixlzw/decompress.py
pyunixlzw-1.0.0.0.dist-info/LICENSE
pyunixlzw-1.0.0.0.dist-info/METADATA
pyunixlzw-1.0.0.0.dist-info/WHEEL
pyunixlzw-1.0.0.0.dist-info/entry_points.txt
pyunixlzw-1.0.0.0.dist-info/top_level.txt
pyunixlzw-1.0.0.0.dist-info/RECORD
