Metadata-Version: 2.2
Name: pyunixlzw
Version: 1.0.0.0
Summary: A pure-Python3 implementation of UNIX compress and decompress.
Author: Justin Berthelot
Maintainer: Justin Berthelot
License: MIT
Project-URL: Repository, https://github.com/jbert1/pyunixlzw
Keywords: compress,decompress,lzw,uncompress,unix
Requires-Python: >3.6
License-File: LICENSE
Provides-Extra: tests
Requires-Dist: unittest; extra == "tests"
